runrms/__init__.py
runrms/__main__.py
runrms/_forward_model.py
runrms/_logging.py
runrms/_rms_api.py
runrms/_utils.py
runrms/exceptions.py
runrms/py.typed
runrms/version.py
runrms/api/__init__.py
runrms/api/proxy.py
runrms/api/worker.py
runrms/config/__init__.py
runrms/config/_rms_config.py
runrms/config/_rms_project.py
runrms/config/_site_config.py
runrms/config/api_config.py
runrms/config/fm_config.py
runrms/config/interactive_config.py
runrms/config/runrms.yml
runrms/executor/__init__.py
runrms/executor/_rms_executor.py
runrms/executor/api_executor.py
runrms/executor/fm_executor.py
runrms/executor/interactive_executor.py
runrms-0.7.3.dist-info/licenses/LICENSE
runrms-0.7.3.dist-info/METADATA
runrms-0.7.3.dist-info/WHEEL
runrms-0.7.3.dist-info/entry_points.txt
runrms-0.7.3.dist-info/top_level.txt
runrms-0.7.3.dist-info/RECORD
