Metadata-Version: 2.4
Name: runrms
Version: 0.7.3
Summary: A utility to open and run AspenTech's RMS application.
Author-email: Equinor <fg-fmu_atlas@equinor.com>
License: GPL-3.0
Project-URL: Homepage, https://github.com/equinor/runrms
Project-URL: Repository, https://github.com/equinor/runrms
Project-URL: Documentation, https://github.com/equinor/runrms
Classifier: Topic :: Scientific/Engineering
Classifier: Topic :: Utilities
Classifier: Operating System :: POSIX :: Linux
Classifier: Programming Language :: Python :: 3.11
Classifier: Programming Language :: Python :: 3.12
Classifier: Programming Language :: Python :: 3.13
Classifier: Natural Language :: English
Requires-Python: >=3.11
License-File: LICENSE
Requires-Dist: packaging
Requires-Dist: pydantic
Requires-Dist: pyyaml
Requires-Dist: pyzmq
Provides-Extra: dev
Requires-Dist: ert>=10.2; extra == "dev"
Requires-Dist: mypy; extra == "dev"
Requires-Dist: pytest; extra == "dev"
Requires-Dist: pytest-cov; extra == "dev"
Requires-Dist: pytest-xdist; extra == "dev"
Requires-Dist: ruff; extra == "dev"
Requires-Dist: types-PyYAML; extra == "dev"
Requires-Dist: types-setuptools; extra == "dev"
Requires-Dist: typing-extensions; extra == "dev"
Dynamic: license-file
